marctools/__init__.py
marctools/marccount.py
marctools/marcpager.py
marctools-0.1.2.dist-info/LICENSE
marctools-0.1.2.dist-info/METADATA
marctools-0.1.2.dist-info/WHEEL
marctools-0.1.2.dist-info/entry_points.txt
marctools-0.1.2.dist-info/top_level.txt
marctools-0.1.2.dist-info/RECORD
